[
    {
        "id": 1,
        "title": "Custom Web Design & Development",
        "content": "Create Your Website, Your way",
        "image": "/img/slid/02.jpg"
    },
    {
        "id": 2,
        "title": " Elevate your professional business with enhanced technology",
        "content": "A website should be the easy part of building a business.",
        "image": "/img/slid/03.jpg"
    },
    {
        "id": 3,
        "title": "Business value through digital products",
        "content": "",
        "image": "/img/slid/01.jpg"
    }
]